pulpcore/__init__.py
pulpcore/client/__init__.py
pulpcore/client/pulp_hugging_face/__init__.py
pulpcore/client/pulp_hugging_face/api_client.py
pulpcore/client/pulp_hugging_face/api_response.py
pulpcore/client/pulp_hugging_face/configuration.py
pulpcore/client/pulp_hugging_face/exceptions.py
pulpcore/client/pulp_hugging_face/py.typed
pulpcore/client/pulp_hugging_face/rest.py
pulpcore/client/pulp_hugging_face/api/__init__.py
pulpcore/client/pulp_hugging_face/api/content_hugging_face_api.py
pulpcore/client/pulp_hugging_face/api/distributions_hugging_face_api.py
pulpcore/client/pulp_hugging_face/api/publications_hugging_face_api.py
pulpcore/client/pulp_hugging_face/api/remotes_hugging_face_api.py
pulpcore/client/pulp_hugging_face/api/repositories_hugging_face_api.py
pulpcore/client/pulp_hugging_face/api/repositories_hugging_face_versions_api.py
pulpcore/client/pulp_hugging_face/models/__init__.py
pulpcore/client/pulp_hugging_face/models/async_operation_response.py
pulpcore/client/pulp_hugging_face/models/content_summary_response.py
pulpcore/client/pulp_hugging_face/models/hugging_face_hugging_face_content.py
pulpcore/client/pulp_hugging_face/models/hugging_face_hugging_face_content_response.py
pulpcore/client/pulp_hugging_face/models/hugging_face_hugging_face_distribution.py
pulpcore/client/pulp_hugging_face/models/hugging_face_hugging_face_distribution_response.py
pulpcore/client/pulp_hugging_face/models/hugging_face_hugging_face_publication.py
pulpcore/client/pulp_hugging_face/models/hugging_face_hugging_face_publication_response.py
pulpcore/client/pulp_hugging_face/models/hugging_face_hugging_face_remote.py
pulpcore/client/pulp_hugging_face/models/hugging_face_hugging_face_remote_response.py
pulpcore/client/pulp_hugging_face/models/hugging_face_hugging_face_remote_response_hidden_fields_inner.py
pulpcore/client/pulp_hugging_face/models/hugging_face_hugging_face_repository.py
pulpcore/client/pulp_hugging_face/models/hugging_face_hugging_face_repository_response.py
pulp_hugging_face_client-0.3.0.dist-info/METADATA
pulp_hugging_face_client-0.3.0.dist-info/WHEEL
pulp_hugging_face_client-0.3.0.dist-info/top_level.txt
pulp_hugging_face_client-0.3.0.dist-info/RECORD
